[{"model": "resume.basicinformation", "pk": 1, "fields": {"name": "\u5415\u5c11\u6ce2", "education": "\u672c\u79d1", "school": "\u5317\u4eac\u79d1\u6280\u5927\u5b66", "major": "\u901a\u4fe1\u5de5\u7a0b"}}, {"model": "resume.basicinformation", "pk": 2, "fields": {"name": "\u5415\u5c11\u6ce2", "education": "\u7855\u58eb", "school": "\u5317\u4eac\u79d1\u6280\u5927\u5b66", "major": "\u4fe1\u606f\u4e0e\u901a\u4fe1\u5de5\u7a0b"}}, {"model": "resume.award", "pk": 1, "fields": {"basic_information": 1, "name": "\u5317\u4eac\u79d1\u6280\u5927\u5b66\u4e09\u597d\u5b66\u751f", "time": "2012-11-01"}}, {"model": "resume.award", "pk": 2, "fields": {"basic_information": 1, "name": "\u5317\u4eac\u79d1\u6280\u5927\u5b66\u4f18\u79c0\u6bd5\u4e1a\u751f", "time": "2015-06-01"}}, {"model": "resume.award", "pk": 3, "fields": {"basic_information": 2, "name": "\u5317\u4eac\u79d1\u6280\u5927\u5b66\u4e09\u597d\u7814\u7a76\u751f", "time": "2016-11-01"}}, {"model": "resume.transcript", "pk": 1, "fields": {"basic_information": 1, "subject": "\u9ad8\u7b49\u6570\u5b66A1", "score": 93}}]